speech_map/__init__.py
speech_map/__main__.py
speech_map/core.py
speech_map/py.typed
speech_map-0.1.2.dist-info/licenses/LICENSE
speech_map-0.1.2.dist-info/WHEEL
speech_map-0.1.2.dist-info/METADATA
speech_map-0.1.2.dist-info/RECORD
