Metadata-Version: 2.4
Name: speech-map
Version: 0.1.2
Summary: Mean Average Precision over n-grams / words with speech features
Keywords: machine learning,speech
Author: Maxime Poli
Author-email: CoML <dev@cognitive-ml.fr>
Requires-Python: >=3.12
License-Expression: MIT
Classifier: Development Status :: 4 - Beta
Classifier: Intended Audience :: Science/Research
Classifier: Operating System :: OS Independent
Classifier: Programming Language :: Python :: 3 :: Only
Classifier: Programming Language :: Python :: 3.12
Classifier: Programming Language :: Python :: 3.13
Classifier: Topic :: Scientific/Engineering
Classifier: Topic :: Scientific/Engineering :: Artificial Intelligence
License-File: LICENSE
Requires-Dist: numpy>=1.26.4
Requires-Dist: polars>=1.36.1
Requires-Dist: torch>=2.6.0
Requires-Dist: tqdm>=4.67.1
Project-URL: repository, https://github.com/bootphon/speech-map
